{"content":"For MVP, avoid overbuilding marketplace-like features (public ratings systems, broad multi-city liquidity mechanics, complex custom telehealth/video, deep EHR integrations) before proving core clinic workflow. Prioritize one reliable workflow: specialist discovery, slot booking, basic intake/consent, and secure admin operations; defer advanced automation and analytics.","source":"web","provider":"websearch","confidence":"MEDIUM","fetched_at":"2026-07-09T13:10:39.426Z","ttl":86400000,"kind":"web"}
